openg2p_g2p_bridge_celery_workers/__init__.py
openg2p_g2p_bridge_celery_workers/app.py
openg2p_g2p_bridge_celery_workers/config.py
openg2p_g2p_bridge_celery_workers/helpers/__init__.py
openg2p_g2p_bridge_celery_workers/helpers/resolve_helper.py
openg2p_g2p_bridge_celery_workers/tasks/__init__.py
openg2p_g2p_bridge_celery_workers/tasks/block_funds_with_bank.py
openg2p_g2p_bridge_celery_workers/tasks/check_funds_with_bank_task.py
openg2p_g2p_bridge_celery_workers/tasks/disburse_funds_from_bank.py
openg2p_g2p_bridge_celery_workers/tasks/mapper_resolution_task.py
openg2p_g2p_bridge_celery_workers/tasks/mt940_processor.py
openg2p_g2p_bridge_celery_workers-1.1.0.dist-info/METADATA
openg2p_g2p_bridge_celery_workers-1.1.0.dist-info/WHEEL
openg2p_g2p_bridge_celery_workers-1.1.0.dist-info/RECORD
